racecontrol/__init__.py
racecontrol/__main__.py
racecontrol/config.py
racecontrol/defaults.py
racecontrol/messages.py
racecontrol-0.0.1a0.dist-info/LICENSE.txt
racecontrol-0.0.1a0.dist-info/METADATA
racecontrol-0.0.1a0.dist-info/RECORD
racecontrol-0.0.1a0.dist-info/WHEEL
racecontrol-0.0.1a0.dist-info/top_level.txt
