Metadata-Version: 2.1
Name: racecontrol
Version: 0.0.1a0
Summary: Racecontrol
Home-page: https://github.com/racecontroll/racecontrol
Author: Matthias Riegler
Author-email: matthias@xvzf.tech
License: UNKNOWN
Platform: UNKNOWN
Classifier: Programming Language :: Python :: 3
Requires-Dist: uvloop
Requires-Dist: aioredis
Requires-Dist: websockets
Requires-Dist: asyncserial
Requires-Dist: flask
Requires-Dist: flask-wtf
Requires-Dist: flask-sqlalchemy
